quadgrid/__init__.py
quadgrid/distance.py
quadgrid/grid.py
quadgrid/qtree.py
quadgrid/qtree_old.py
quadgrid-0.2.1.dist-info/METADATA
quadgrid-0.2.1.dist-info/WHEEL
quadgrid-0.2.1.dist-info/licenses/LICENSE
quadgrid-0.2.1.dist-info/RECORD
