Metadata-Version: 2.4
Name: quadgrid
Version: 0.2.1
Summary: Quadtree grid generator
Project-URL: Homepage, https://github.com/MutaharChalmers/quadgrid
Author-email: Mutahar Chalmers <mutahar.chalmers@gmail.com>
License: MIT License
License-File: LICENSE
Classifier: Development Status :: 4 - Beta
Classifier: Intended Audience :: Science/Research
Classifier: License :: OSI Approved :: MIT License
Classifier: Operating System :: OS Independent
Classifier: Programming Language :: Python :: 3
Classifier: Topic :: Scientific/Engineering :: GIS
Requires-Python: >=3.11
Requires-Dist: geopandas>=1.0.0
Requires-Dist: numpy>=1.26.4
Requires-Dist: pandas>=2.0
Requires-Dist: shapely>=2.0.0
Requires-Dist: xarray>=2024.1.0
